dec_opt/__init__.py
dec_opt/compression.py
dec_opt/data_reader.py
dec_opt/dec_gd.py
dec_opt/experiment.py
dec_opt/gossip_matrix.py
dec_opt/linear_regression.py
dec_opt/logistic_regression.py
dec_opt/non_linear_regression.py
dec_opt/pickle_data.py
dec_opt/utils.py
decopt-2.1.8.dist-info/LICENSE
decopt-2.1.8.dist-info/METADATA
decopt-2.1.8.dist-info/WHEEL
decopt-2.1.8.dist-info/top_level.txt
decopt-2.1.8.dist-info/RECORD
