Metadata-Version: 2.1
Name: decopt
Version: 2.1.8
Summary: State of the art decentralized optimization library
Home-page: https://github.com/anishacharya/decentralized-opt
Author: Anish Acharya
Author-email: anishacharya@utexas.edu
License: UNKNOWN
Platform: UNKNOWN
Classifier: Programming Language :: Python :: 3
Classifier: License :: OSI Approved :: MIT License
Classifier: Operating System :: OS Independent
Requires-Python: >=3.6
